<?xml version="1.0" encoding="UTF-8"?>
<Export generator="IRIS" version="26" zv="IRIS for UNIX (Apple Mac OS X for x86-64) 2018.2 (Build 490U)" ts="2019-04-23 11:18:10">
<Class name="MQTT.DemoProcessRoutingRule">
<Description>
</Description>
<Super>Ens.Rule.Definition</Super>
<TimeChanged>65126,39011.717174</TimeChanged>
<TimeCreated>65126,38470.15954</TimeCreated>

<Parameter name="RuleAssistClass">
<Default>EnsLib.MsgRouter.VDocRuleAssist</Default>
</Parameter>

<XData name="RuleDefinition">
<XMLNamespace>http://www.intersystems.com/rule</XMLNamespace>
<Data><![CDATA[
<ruleDefinition alias="" context="EnsLib.MsgRouter.VDocRoutingEngine" production="MQTT.PassThroughDemo">
<ruleSet name="" effectiveBegin="" effectiveEnd="">
<rule name="">
</rule>
<send transform="MQTT.VDocToStringContainer" target="MQTTOut"></send>
</ruleSet>
</ruleDefinition>
]]></Data>
</XData>
</Class>
</Export>
